agentic_tools/__init__.py
agentic_tools-0.2.1.dist-info/licenses/LICENSE
agentic_tools-0.2.1.dist-info/METADATA
agentic_tools-0.2.1.dist-info/WHEEL
agentic_tools-0.2.1.dist-info/top_level.txt
agentic_tools-0.2.1.dist-info/RECORD
