Metadata-Version: 2.4
Name: agentic-tools
Version: 0.2.1
Summary: A toolset for agentic workflows
Home-page: https://github.com/AxelGard/agentic-tools
Author: Axel Gard
Author-email: axel.gard@tutanota.com
Classifier: Programming Language :: Python :: 3
Classifier: License :: OSI Approved :: MIT License
Classifier: Operating System :: OS Independent
Requires-Python: >=3.7
License-File: LICENSE
Requires-Dist: langchain-ollama
Requires-Dist: langchain
Provides-Extra: dev
Requires-Dist: pytest; extra == "dev"
Requires-Dist: black; extra == "dev"
Requires-Dist: build; extra == "dev"
Dynamic: author
Dynamic: author-email
Dynamic: classifier
Dynamic: description
Dynamic: description-content-type
Dynamic: home-page
Dynamic: license-file
Dynamic: provides-extra
Dynamic: requires-dist
Dynamic: requires-python
Dynamic: summary
